<?xml version="1.0" encoding="utf-8"?>
<Symbolconfiguration xmlns="http://www.3s-software.com/schemas/Symbolconfiguration.xsd">
  <Header>
    <Version>3.5.11.0</Version>
    <SymbolConfigObject version="3.5.11.10" runtimeid="3.5.11.30" libversion="3.5.11.0" compiler="3.5.11.30" lmm="3.5.11.30" profile="XSOFT-CODESYS V3.5.11+" settings="SupportOPCUA, LayoutCalculator=OptimizedClientSideLayoutCalculator" />
    <ProjectInfo name="Acionamento da esteira transportadora" devicename="Device" appname="Application" />
  </Header>
  <TypeList>
    <TypeSimple name="T_BOOL" size="1" swapsize="0" typeclass="Bool" iecname="BOOL" />
  </TypeList>
  <NodeList>
    <Node name="Application">
      <Node name="PLC_PRG">
        <Node name="Emergencia" type="T_BOOL" access="ReadWrite" />
        <Node name="Esteira" type="T_BOOL" access="ReadWrite" />
        <Node name="Sensor" type="T_BOOL" access="ReadWrite" />
        <Node name="Start" type="T_BOOL" access="ReadWrite" />
        <Node name="Start_Light" type="T_BOOL" access="ReadWrite" />
        <Node name="Stop" type="T_BOOL" access="ReadWrite" />
        <Node name="Stop_Light" type="T_BOOL" access="ReadWrite" />
      </Node>
    </Node>
  </NodeList>
</Symbolconfiguration>